prusek_spheroid/ContoursClassGUI.py
prusek_spheroid/GUI.py
prusek_spheroid/GradientDescentGUI.py
prusek_spheroid/calculate_iou.py
prusek_spheroid/characteristic_functions.py
prusek_spheroid/conversion.py
prusek_spheroid/file_management.py
prusek_spheroid/image_processing.py
prusek_spheroid/merge_directories.py
prusek_spheroid/methods.py
prusek_spheroid/metrics.py
prusek_spheroid/selection_dialog.py
prusek_spheroid-6.8.dist-info/METADATA
prusek_spheroid-6.8.dist-info/WHEEL
prusek_spheroid-6.8.dist-info/top_level.txt
prusek_spheroid-6.8.dist-info/RECORD
