Metadata-Version: 2.1
Name: prusek_spheroid
Version: 6.8
Summary: Spheroid segmentation package
Home-page: https://github.com/michalprusek/prusek-spheroid
Author: Michal Prusek
Author-email: prusemic@cvut.cz
Requires-Dist: numpy
Requires-Dist: opencv-python
Requires-Dist: scikit-image
Requires-Dist: scikit-learn
Requires-Dist: shapely
Requires-Dist: threadpoolctl
Requires-Dist: matplotlib
Requires-Dist: rasterio
Requires-Dist: pandas
Requires-Dist: openpyxl
Requires-Dist: torch
Requires-Dist: imagehash
Requires-Dist: joblib
